PySimpleGUIQt/PySimpleGUIQt.py
PySimpleGUIQt/__init__.py
PySimpleGUIQt-0.34.0.dist-info/METADATA
PySimpleGUIQt-0.34.0.dist-info/WHEEL
PySimpleGUIQt-0.34.0.dist-info/top_level.txt
PySimpleGUIQt-0.34.0.dist-info/RECORD
